{
  "game_id": 0,
  "players": [
    {"id": 1, "name": "pedro", "score": 0, "answered": true, "is_human": true},
    {"id": 2, "name": "jordan", "score": 100, "answered": false, "is_human": true},
    {"id": 3, "name": "qanta", "score": 50, "answered": false, "is_human": false}
  ],
  "text": "Who was this american president who was born in a logged cabin?",
  "buzzes": [
    {"player_id": 1, "correct": false, "guess": ""},
    {"player_id": 3, "correct": false, "guess": "george_washington"}
  ],
  "answer": null,
  "is_end_of_question": false
}